{"namedChunkGroups":{"polyfill":{"name":"polyfill","assets":[{"name":"webpack-runtime-1f5a32cec90f281ac700.js","size":4000},{"name":"polyfill-de6f229c0a3977155403.js","size":82643}],"filteredAssets":0,"assetsSize":86643,"filteredAuxiliaryAssets":2,"auxiliaryAssetsSize":217189},"app":{"name":"app","assets":[{"name":"webpack-runtime-1f5a32cec90f281ac700.js","size":4000},{"name":"framework-341c3c82f92be86019fb.js","size":128971},{"name":"styles.b411d1bf17f48164193a.css","size":17764},{"name":"app-8bff5f2c6666b56da8e4.js","size":85458}],"filteredAssets":0,"assetsSize":236193,"filteredAuxiliaryAssets":55,"auxiliaryAssetsSize":1821658},"component---src-pages-404-js":{"name":"component---src-pages-404-js","assets":[{"name":"commons-47e3acdd96956e0eef1b.js","size":16481},{"name":"component---src-pages-404-js-f7928806f3dd869f532e.js","size":614}],"filteredAssets":0,"assetsSize":17095,"filteredAuxiliaryAssets":2,"auxiliaryAssetsSize":69510},"component---src-pages-index-js":{"name":"component---src-pages-index-js","assets":[{"name":"commons-47e3acdd96956e0eef1b.js","size":16481},{"name":"component---src-pages-index-js-aec717eff15159c28caa.js","size":2906}],"filteredAssets":0,"assetsSize":19387,"filteredAuxiliaryAssets":2,"auxiliaryAssetsSize":73658},"component---src-pages-using-typescript-tsx":{"name":"component---src-pages-using-typescript-tsx","assets":[{"name":"commons-47e3acdd96956e0eef1b.js","size":16481},{"name":"component---src-pages-using-typescript-tsx-ec89e82605e2a0c5e9c7.js","size":1373}],"filteredAssets":0,"assetsSize":17854,"filteredAuxiliaryAssets":2,"auxiliaryAssetsSize":70551},"component---src-templates-blog-post-js":{"name":"component---src-templates-blog-post-js","assets":[{"name":"commons-47e3acdd96956e0eef1b.js","size":16481},{"name":"component---src-templates-blog-post-js-d98f37cf8e8d6f4491c2.js","size":2842}],"filteredAssets":0,"assetsSize":19323,"filteredAuxiliaryAssets":2,"auxiliaryAssetsSize":73922}},"assetsByChunkName":{"polyfill":["webpack-runtime-1f5a32cec90f281ac700.js","polyfill-de6f229c0a3977155403.js"],"app":["webpack-runtime-1f5a32cec90f281ac700.js","framework-341c3c82f92be86019fb.js","styles.b411d1bf17f48164193a.css","app-8bff5f2c6666b56da8e4.js"],"component---src-pages-404-js":["commons-47e3acdd96956e0eef1b.js","component---src-pages-404-js-f7928806f3dd869f532e.js"],"component---src-pages-index-js":["commons-47e3acdd96956e0eef1b.js","component---src-pages-index-js-aec717eff15159c28caa.js"],"component---src-pages-using-typescript-tsx":["commons-47e3acdd96956e0eef1b.js","component---src-pages-using-typescript-tsx-ec89e82605e2a0c5e9c7.js"],"component---src-templates-blog-post-js":["commons-47e3acdd96956e0eef1b.js","component---src-templates-blog-post-js-d98f37cf8e8d6f4491c2.js"]},"childAssetsByChunkName":{}}